setup.py
rainbow_django/__init__.py
rainbow_django/admin.py
rainbow_django/models.py
rainbow_django/tests.py
rainbow_django/urls.py
rainbow_django/views.py
rainbow_django.egg-info/PKG-INFO
rainbow_django.egg-info/SOURCES.txt
rainbow_django.egg-info/dependency_links.txt
rainbow_django.egg-info/requires.txt
rainbow_django.egg-info/top_level.txt
rainbow_django/migrations/__init__.py