Metadata-Version: 1.0
Name: rainbow-django
Version: 0.2
Summary: Rainbow Biz side Sdk for Django
Home-page: https://github.com/jeffkit/rainbow-django
Author: jeff kit
Author-email: bbmyth@gmail.com
License: UNKNOWN
Platform: UNKNOWN
